git_pr/__init__.py
git_pr/git_pr.py
gitprprod-0.0.4.dist-info/METADATA
gitprprod-0.0.4.dist-info/WHEEL
gitprprod-0.0.4.dist-info/entry_points.txt
gitprprod-0.0.4.dist-info/top_level.txt
gitprprod-0.0.4.dist-info/RECORD
